{"name":"ssh-keygen","slug":"ssh-keygen","count":1,"postlist":[{"title":"ssh keygen","uid":"8a8cf02982a981a3981c312011f99772","slug":"ssh-keygen","date":"2025-01-07T09:06:00.000Z","updated":"2025-01-07T09:06:00.000Z","comments":true,"path":"api/articles/ssh-keygen.json","keywords":null,"cover":"https://img.kidwen.top/file/AgACAgUAAyEGAASHUuUOAAMKZ8Uk3Z0SXl4caws_sVUAATJxcK-wAAIxwTEb6dopVs78RNHffPBfAQADAgADeAADNgQ.png","text":"一般来说，一个github账号和一个gitlab账号，需要生成两个公钥和私钥，分别用于github和gitlab。下面介绍如何生成公钥和私钥。并且配置confi...","permalink":"/post/ssh-keygen","photos":[],"count_time":{"symbolsCount":"1.4k","symbolsTime":"1 mins."},"categories":[{"name":"GIT","slug":"GIT","count":2,"path":"api/categories/GIT.json"}],"tags":[{"name":"ssh-keygen","slug":"ssh-keygen","count":1,"path":"api/tags/ssh-keygen.json"}],"author":{"name":"Kidwen","slug":"blog-author","avatar":"https://avatars.githubusercontent.com/u/38277891?v=4","link":"/","description":"Frontend","socials":{"github":"https://github.com/kidwen","twitter":"","stackoverflow":"","wechat":"","qq":"","weibo":"","zhihu":"","csdn":"","juejin":"","customs":{}}}}]}